{
  "manifestVersion": "3.2",
  "proxies": [
    {
      "address": "0x0A3A06b98c59Fb69653D4686709F8d722E953FE3",
      "txHash": "0xb7c46d6e3f8aa5c7aa2aa21c2efe994bbcc8b020c85de4f5282b6e53a2a0e29a",
      "kind": "uups"
    }
  ],
  "impls": {
    "46e9727fa8918e4d0772a6ae657b9c77d805d80d835863d252d5410f706e476b": {
      "address": "0x196891AB86c8C9f191dB774d6082d0E2f4b53767",
      "txHash": "0xf1ede331bc472cf2d19f95410ebfcd7ad4157c17f240b9f76cfff4f77cf09cd0",
      "layout": {
        "solcVersion": "0.8.17",
        "storage": [
          {
            "label": "_initialized",
            "offset": 0,
            "slot": "0",
            "type": "t_uint8",
            "contract": "Initializable",
            "src": "@openzeppelin/contracts-upgradeable/proxy/utils/Initializable.sol:62",
            "retypedFrom": "bool"
          },
          {
            "label": "_initializing",
            "offset": 1,
            "slot": "0",
            "type": "t_bool",
            "contract": "Initializable",
            "src": "@openzeppelin/contracts-upgradeable/proxy/utils/Initializable.sol:67"
          },
          {
            "label": "__gap",
            "offset": 0,
            "slot": "1",
            "type": "t_array(t_uint256)50_storage",
            "contract": "ContextUpgradeable",
            "src": "@openzeppelin/contracts-upgradeable/utils/ContextUpgradeable.sol:36"
          },
          {
            "label": "__gap",
            "offset": 0,
            "slot": "51",
            "type": "t_array(t_uint256)50_storage",
            "contract": "ERC165Upgradeable",
            "src": "@openzeppelin/contracts-upgradeable/utils/introspection/ERC165Upgradeable.sol:41"
          },
          {
            "label": "_name",
            "offset": 0,
            "slot": "101",
            "type": "t_string_storage",
            "contract": "ERC721Upgradeable",
            "src": "@openzeppelin/contracts-upgradeable/token/ERC721/ERC721Upgradeable.sol:25"
          },
          {
            "label": "_symbol",
            "offset": 0,
            "slot": "102",
            "type": "t_string_storage",
            "contract": "ERC721Upgradeable",
            "src": "@openzeppelin/contracts-upgradeable/token/ERC721/ERC721Upgradeable.sol:28"
          },
          {
            "label": "_owners",
            "offset": 0,
            "slot": "103",
            "type": "t_mapping(t_uint256,t_address)",
            "contract": "ERC721Upgradeable",
            "src": "@openzeppelin/contracts-upgradeable/token/ERC721/ERC721Upgradeable.sol:31"
          },
          {
            "label": "_balances",
            "offset": 0,
            "slot": "104",
            "type": "t_mapping(t_address,t_uint256)",
            "contract": "ERC721Upgradeable",
            "src": "@openzeppelin/contracts-upgradeable/token/ERC721/ERC721Upgradeable.sol:34"
          },
          {
            "label": "_tokenApprovals",
            "offset": 0,
            "slot": "105",
            "type": "t_mapping(t_uint256,t_address)",
            "contract": "ERC721Upgradeable",
            "src": "@openzeppelin/contracts-upgradeable/token/ERC721/ERC721Upgradeable.sol:37"
          },
          {
            "label": "_operatorApprovals",
            "offset": 0,
            "slot": "106",
            "type": "t_mapping(t_address,t_mapping(t_address,t_bool))",
            "contract": "ERC721Upgradeable",
            "src": "@openzeppelin/contracts-upgradeable/token/ERC721/ERC721Upgradeable.sol:40"
          },
          {
            "label": "__gap",
            "offset": 0,
            "slot": "107",
            "type": "t_array(t_uint256)44_storage",
            "contract": "ERC721Upgradeable",
            "src": "@openzeppelin/contracts-upgradeable/token/ERC721/ERC721Upgradeable.sol:532"
          },
          {
            "label": "_tokenURIs",
            "offset": 0,
            "slot": "151",
            "type": "t_mapping(t_uint256,t_string_storage)",
            "contract": "ERC721URIStorageUpgradeable",
            "src": "@openzeppelin/contracts-upgradeable/token/ERC721/extensions/ERC721URIStorageUpgradeable.sol:21"
          },
          {
            "label": "__gap",
            "offset": 0,
            "slot": "152",
            "type": "t_array(t_uint256)49_storage",
            "contract": "ERC721URIStorageUpgradeable",
            "src": "@openzeppelin/contracts-upgradeable/token/ERC721/extensions/ERC721URIStorageUpgradeable.sol:74"
          },
          {
            "label": "__gap",
            "offset": 0,
            "slot": "201",
            "type": "t_array(t_uint256)50_storage",
            "contract": "ERC721BurnableUpgradeable",
            "src": "@openzeppelin/contracts-upgradeable/token/ERC721/extensions/ERC721BurnableUpgradeable.sol:38"
          },
          {
            "label": "_owner",
            "offset": 0,
            "slot": "251",
            "type": "t_address",
            "contract": "OwnableUpgradeable",
            "src": "@openzeppelin/contracts-upgradeable/access/OwnableUpgradeable.sol:22"
          },
          {
            "label": "__gap",
            "offset": 0,
            "slot": "252",
            "type": "t_array(t_uint256)49_storage",
            "contract": "OwnableUpgradeable",
            "src": "@openzeppelin/contracts-upgradeable/access/OwnableUpgradeable.sol:94"
          },
          {
            "label": "__gap",
            "offset": 0,
            "slot": "301",
            "type": "t_array(t_uint256)50_storage",
            "contract": "ERC1967UpgradeUpgradeable",
            "src": "@openzeppelin/contracts-upgradeable/proxy/ERC1967/ERC1967UpgradeUpgradeable.sol:211"
          },
          {
            "label": "__gap",
            "offset": 0,
            "slot": "351",
            "type": "t_array(t_uint256)50_storage",
            "contract": "UUPSUpgradeable",
            "src": "@openzeppelin/contracts-upgradeable/proxy/utils/UUPSUpgradeable.sol:107"
          },
          {
            "label": "_tokenIdCounter",
            "offset": 0,
            "slot": "401",
            "type": "t_struct(Counter)2494_storage",
            "contract": "MyNFT",
            "src": "contracts/MyNFT.sol:15"
          }
        ],
        "types": {
          "t_address": {
            "label": "address",
            "numberOfBytes": "20"
          },
          "t_array(t_uint256)44_storage": {
            "label": "uint256[44]",
            "numberOfBytes": "1408"
          },
          "t_array(t_uint256)49_storage": {
            "label": "uint256[49]",
            "numberOfBytes": "1568"
          },
          "t_array(t_uint256)50_storage": {
            "label": "uint256[50]",
            "numberOfBytes": "1600"
          },
          "t_bool": {
            "label": "bool",
            "numberOfBytes": "1"
          },
          "t_mapping(t_address,t_bool)": {
            "label": "mapping(address => bool)",
            "numberOfBytes": "32"
          },
          "t_mapping(t_address,t_mapping(t_address,t_bool))": {
            "label": "mapping(address => mapping(address => bool))",
            "numberOfBytes": "32"
          },
          "t_mapping(t_address,t_uint256)": {
            "label": "mapping(address => uint256)",
            "numberOfBytes": "32"
          },
          "t_mapping(t_uint256,t_address)": {
            "label": "mapping(uint256 => address)",
            "numberOfBytes": "32"
          },
          "t_mapping(t_uint256,t_string_storage)": {
            "label": "mapping(uint256 => string)",
            "numberOfBytes": "32"
          },
          "t_string_storage": {
            "label": "string",
            "numberOfBytes": "32"
          },
          "t_struct(Counter)2494_storage": {
            "label": "struct CountersUpgradeable.Counter",
            "members": [
              {
                "label": "_value",
                "type": "t_uint256",
                "offset": 0,
                "slot": "0"
              }
            ],
            "numberOfBytes": "32"
          },
          "t_uint256": {
            "label": "uint256",
            "numberOfBytes": "32"
          },
          "t_uint8": {
            "label": "uint8",
            "numberOfBytes": "1"
          }
        }
      }
    },
    "6ec718f1158abfc1a4f3b72d463f118074a01fdf7b66c347ab1dfa660fbb6a77": {
      "address": "0xE97deC68CcEb7668a5e8A5d03E07e59c41C38161",
      "txHash": "0x78c3994934d9caa9c979d1281e23025d7bd0a75e45b1341c886826db5b50394a",
      "layout": {
        "solcVersion": "0.8.17",
        "storage": [
          {
            "label": "_initialized",
            "offset": 0,
            "slot": "0",
            "type": "t_uint8",
            "contract": "Initializable",
            "src": "@openzeppelin/contracts-upgradeable/proxy/utils/Initializable.sol:62",
            "retypedFrom": "bool"
          },
          {
            "label": "_initializing",
            "offset": 1,
            "slot": "0",
            "type": "t_bool",
            "contract": "Initializable",
            "src": "@openzeppelin/contracts-upgradeable/proxy/utils/Initializable.sol:67"
          },
          {
            "label": "__gap",
            "offset": 0,
            "slot": "1",
            "type": "t_array(t_uint256)50_storage",
            "contract": "ContextUpgradeable",
            "src": "@openzeppelin/contracts-upgradeable/utils/ContextUpgradeable.sol:36"
          },
          {
            "label": "__gap",
            "offset": 0,
            "slot": "51",
            "type": "t_array(t_uint256)50_storage",
            "contract": "ERC165Upgradeable",
            "src": "@openzeppelin/contracts-upgradeable/utils/introspection/ERC165Upgradeable.sol:41"
          },
          {
            "label": "_name",
            "offset": 0,
            "slot": "101",
            "type": "t_string_storage",
            "contract": "ERC721Upgradeable",
            "src": "@openzeppelin/contracts-upgradeable/token/ERC721/ERC721Upgradeable.sol:25"
          },
          {
            "label": "_symbol",
            "offset": 0,
            "slot": "102",
            "type": "t_string_storage",
            "contract": "ERC721Upgradeable",
            "src": "@openzeppelin/contracts-upgradeable/token/ERC721/ERC721Upgradeable.sol:28"
          },
          {
            "label": "_owners",
            "offset": 0,
            "slot": "103",
            "type": "t_mapping(t_uint256,t_address)",
            "contract": "ERC721Upgradeable",
            "src": "@openzeppelin/contracts-upgradeable/token/ERC721/ERC721Upgradeable.sol:31"
          },
          {
            "label": "_balances",
            "offset": 0,
            "slot": "104",
            "type": "t_mapping(t_address,t_uint256)",
            "contract": "ERC721Upgradeable",
            "src": "@openzeppelin/contracts-upgradeable/token/ERC721/ERC721Upgradeable.sol:34"
          },
          {
            "label": "_tokenApprovals",
            "offset": 0,
            "slot": "105",
            "type": "t_mapping(t_uint256,t_address)",
            "contract": "ERC721Upgradeable",
            "src": "@openzeppelin/contracts-upgradeable/token/ERC721/ERC721Upgradeable.sol:37"
          },
          {
            "label": "_operatorApprovals",
            "offset": 0,
            "slot": "106",
            "type": "t_mapping(t_address,t_mapping(t_address,t_bool))",
            "contract": "ERC721Upgradeable",
            "src": "@openzeppelin/contracts-upgradeable/token/ERC721/ERC721Upgradeable.sol:40"
          },
          {
            "label": "__gap",
            "offset": 0,
            "slot": "107",
            "type": "t_array(t_uint256)44_storage",
            "contract": "ERC721Upgradeable",
            "src": "@openzeppelin/contracts-upgradeable/token/ERC721/ERC721Upgradeable.sol:532"
          },
          {
            "label": "_tokenURIs",
            "offset": 0,
            "slot": "151",
            "type": "t_mapping(t_uint256,t_string_storage)",
            "contract": "ERC721URIStorageUpgradeable",
            "src": "@openzeppelin/contracts-upgradeable/token/ERC721/extensions/ERC721URIStorageUpgradeable.sol:21"
          },
          {
            "label": "__gap",
            "offset": 0,
            "slot": "152",
            "type": "t_array(t_uint256)49_storage",
            "contract": "ERC721URIStorageUpgradeable",
            "src": "@openzeppelin/contracts-upgradeable/token/ERC721/extensions/ERC721URIStorageUpgradeable.sol:74"
          },
          {
            "label": "__gap",
            "offset": 0,
            "slot": "201",
            "type": "t_array(t_uint256)50_storage",
            "contract": "ERC721BurnableUpgradeable",
            "src": "@openzeppelin/contracts-upgradeable/token/ERC721/extensions/ERC721BurnableUpgradeable.sol:38"
          },
          {
            "label": "_owner",
            "offset": 0,
            "slot": "251",
            "type": "t_address",
            "contract": "OwnableUpgradeable",
            "src": "@openzeppelin/contracts-upgradeable/access/OwnableUpgradeable.sol:22"
          },
          {
            "label": "__gap",
            "offset": 0,
            "slot": "252",
            "type": "t_array(t_uint256)49_storage",
            "contract": "OwnableUpgradeable",
            "src": "@openzeppelin/contracts-upgradeable/access/OwnableUpgradeable.sol:94"
          },
          {
            "label": "__gap",
            "offset": 0,
            "slot": "301",
            "type": "t_array(t_uint256)50_storage",
            "contract": "ERC1967UpgradeUpgradeable",
            "src": "@openzeppelin/contracts-upgradeable/proxy/ERC1967/ERC1967UpgradeUpgradeable.sol:211"
          },
          {
            "label": "__gap",
            "offset": 0,
            "slot": "351",
            "type": "t_array(t_uint256)50_storage",
            "contract": "UUPSUpgradeable",
            "src": "@openzeppelin/contracts-upgradeable/proxy/utils/UUPSUpgradeable.sol:107"
          },
          {
            "label": "_tokenIdCounter",
            "offset": 0,
            "slot": "401",
            "type": "t_struct(Counter)2494_storage",
            "contract": "MyNFT",
            "src": "contracts/MyNFT.sol:15"
          }
        ],
        "types": {
          "t_address": {
            "label": "address",
            "numberOfBytes": "20"
          },
          "t_array(t_uint256)44_storage": {
            "label": "uint256[44]",
            "numberOfBytes": "1408"
          },
          "t_array(t_uint256)49_storage": {
            "label": "uint256[49]",
            "numberOfBytes": "1568"
          },
          "t_array(t_uint256)50_storage": {
            "label": "uint256[50]",
            "numberOfBytes": "1600"
          },
          "t_bool": {
            "label": "bool",
            "numberOfBytes": "1"
          },
          "t_mapping(t_address,t_bool)": {
            "label": "mapping(address => bool)",
            "numberOfBytes": "32"
          },
          "t_mapping(t_address,t_mapping(t_address,t_bool))": {
            "label": "mapping(address => mapping(address => bool))",
            "numberOfBytes": "32"
          },
          "t_mapping(t_address,t_uint256)": {
            "label": "mapping(address => uint256)",
            "numberOfBytes": "32"
          },
          "t_mapping(t_uint256,t_address)": {
            "label": "mapping(uint256 => address)",
            "numberOfBytes": "32"
          },
          "t_mapping(t_uint256,t_string_storage)": {
            "label": "mapping(uint256 => string)",
            "numberOfBytes": "32"
          },
          "t_string_storage": {
            "label": "string",
            "numberOfBytes": "32"
          },
          "t_struct(Counter)2494_storage": {
            "label": "struct CountersUpgradeable.Counter",
            "members": [
              {
                "label": "_value",
                "type": "t_uint256",
                "offset": 0,
                "slot": "0"
              }
            ],
            "numberOfBytes": "32"
          },
          "t_uint256": {
            "label": "uint256",
            "numberOfBytes": "32"
          },
          "t_uint8": {
            "label": "uint8",
            "numberOfBytes": "1"
          }
        }
      }
    },
    "abafe63bb56b188bc23354c3c64eedd01da05e018d6037fe52dfe450b988a137": {
      "address": "0xFd9D481d8732824EF46A914a81A3fDfdbA057DD6",
      "txHash": "0xdb15322d24b0cae536236a3effd2e8fb7ce958c02583ed04a91df4bcfc81039f",
      "layout": {
        "solcVersion": "0.8.17",
        "storage": [
          {
            "label": "_initialized",
            "offset": 0,
            "slot": "0",
            "type": "t_uint8",
            "contract": "Initializable",
            "src": "@openzeppelin/contracts-upgradeable/proxy/utils/Initializable.sol:62",
            "retypedFrom": "bool"
          },
          {
            "label": "_initializing",
            "offset": 1,
            "slot": "0",
            "type": "t_bool",
            "contract": "Initializable",
            "src": "@openzeppelin/contracts-upgradeable/proxy/utils/Initializable.sol:67"
          },
          {
            "label": "__gap",
            "offset": 0,
            "slot": "1",
            "type": "t_array(t_uint256)50_storage",
            "contract": "ContextUpgradeable",
            "src": "@openzeppelin/contracts-upgradeable/utils/ContextUpgradeable.sol:36"
          },
          {
            "label": "__gap",
            "offset": 0,
            "slot": "51",
            "type": "t_array(t_uint256)50_storage",
            "contract": "ERC165Upgradeable",
            "src": "@openzeppelin/contracts-upgradeable/utils/introspection/ERC165Upgradeable.sol:41"
          },
          {
            "label": "_name",
            "offset": 0,
            "slot": "101",
            "type": "t_string_storage",
            "contract": "ERC721Upgradeable",
            "src": "@openzeppelin/contracts-upgradeable/token/ERC721/ERC721Upgradeable.sol:25"
          },
          {
            "label": "_symbol",
            "offset": 0,
            "slot": "102",
            "type": "t_string_storage",
            "contract": "ERC721Upgradeable",
            "src": "@openzeppelin/contracts-upgradeable/token/ERC721/ERC721Upgradeable.sol:28"
          },
          {
            "label": "_owners",
            "offset": 0,
            "slot": "103",
            "type": "t_mapping(t_uint256,t_address)",
            "contract": "ERC721Upgradeable",
            "src": "@openzeppelin/contracts-upgradeable/token/ERC721/ERC721Upgradeable.sol:31"
          },
          {
            "label": "_balances",
            "offset": 0,
            "slot": "104",
            "type": "t_mapping(t_address,t_uint256)",
            "contract": "ERC721Upgradeable",
            "src": "@openzeppelin/contracts-upgradeable/token/ERC721/ERC721Upgradeable.sol:34"
          },
          {
            "label": "_tokenApprovals",
            "offset": 0,
            "slot": "105",
            "type": "t_mapping(t_uint256,t_address)",
            "contract": "ERC721Upgradeable",
            "src": "@openzeppelin/contracts-upgradeable/token/ERC721/ERC721Upgradeable.sol:37"
          },
          {
            "label": "_operatorApprovals",
            "offset": 0,
            "slot": "106",
            "type": "t_mapping(t_address,t_mapping(t_address,t_bool))",
            "contract": "ERC721Upgradeable",
            "src": "@openzeppelin/contracts-upgradeable/token/ERC721/ERC721Upgradeable.sol:40"
          },
          {
            "label": "__gap",
            "offset": 0,
            "slot": "107",
            "type": "t_array(t_uint256)44_storage",
            "contract": "ERC721Upgradeable",
            "src": "@openzeppelin/contracts-upgradeable/token/ERC721/ERC721Upgradeable.sol:532"
          },
          {
            "label": "_tokenURIs",
            "offset": 0,
            "slot": "151",
            "type": "t_mapping(t_uint256,t_string_storage)",
            "contract": "ERC721URIStorageUpgradeable",
            "src": "@openzeppelin/contracts-upgradeable/token/ERC721/extensions/ERC721URIStorageUpgradeable.sol:21"
          },
          {
            "label": "__gap",
            "offset": 0,
            "slot": "152",
            "type": "t_array(t_uint256)49_storage",
            "contract": "ERC721URIStorageUpgradeable",
            "src": "@openzeppelin/contracts-upgradeable/token/ERC721/extensions/ERC721URIStorageUpgradeable.sol:74"
          },
          {
            "label": "__gap",
            "offset": 0,
            "slot": "201",
            "type": "t_array(t_uint256)50_storage",
            "contract": "ERC721BurnableUpgradeable",
            "src": "@openzeppelin/contracts-upgradeable/token/ERC721/extensions/ERC721BurnableUpgradeable.sol:38"
          },
          {
            "label": "_owner",
            "offset": 0,
            "slot": "251",
            "type": "t_address",
            "contract": "OwnableUpgradeable",
            "src": "@openzeppelin/contracts-upgradeable/access/OwnableUpgradeable.sol:22"
          },
          {
            "label": "__gap",
            "offset": 0,
            "slot": "252",
            "type": "t_array(t_uint256)49_storage",
            "contract": "OwnableUpgradeable",
            "src": "@openzeppelin/contracts-upgradeable/access/OwnableUpgradeable.sol:94"
          },
          {
            "label": "__gap",
            "offset": 0,
            "slot": "301",
            "type": "t_array(t_uint256)50_storage",
            "contract": "ERC1967UpgradeUpgradeable",
            "src": "@openzeppelin/contracts-upgradeable/proxy/ERC1967/ERC1967UpgradeUpgradeable.sol:211"
          },
          {
            "label": "__gap",
            "offset": 0,
            "slot": "351",
            "type": "t_array(t_uint256)50_storage",
            "contract": "UUPSUpgradeable",
            "src": "@openzeppelin/contracts-upgradeable/proxy/utils/UUPSUpgradeable.sol:107"
          },
          {
            "label": "_tokenIdCounter",
            "offset": 0,
            "slot": "401",
            "type": "t_struct(Counter)2494_storage",
            "contract": "MyNFT",
            "src": "contracts/MyNFT.sol:15"
          },
          {
            "label": "currentIdCount",
            "offset": 0,
            "slot": "402",
            "type": "t_uint256",
            "contract": "MyNFT",
            "src": "contracts/MyNFT.sol:33"
          }
        ],
        "types": {
          "t_address": {
            "label": "address",
            "numberOfBytes": "20"
          },
          "t_array(t_uint256)44_storage": {
            "label": "uint256[44]",
            "numberOfBytes": "1408"
          },
          "t_array(t_uint256)49_storage": {
            "label": "uint256[49]",
            "numberOfBytes": "1568"
          },
          "t_array(t_uint256)50_storage": {
            "label": "uint256[50]",
            "numberOfBytes": "1600"
          },
          "t_bool": {
            "label": "bool",
            "numberOfBytes": "1"
          },
          "t_mapping(t_address,t_bool)": {
            "label": "mapping(address => bool)",
            "numberOfBytes": "32"
          },
          "t_mapping(t_address,t_mapping(t_address,t_bool))": {
            "label": "mapping(address => mapping(address => bool))",
            "numberOfBytes": "32"
          },
          "t_mapping(t_address,t_uint256)": {
            "label": "mapping(address => uint256)",
            "numberOfBytes": "32"
          },
          "t_mapping(t_uint256,t_address)": {
            "label": "mapping(uint256 => address)",
            "numberOfBytes": "32"
          },
          "t_mapping(t_uint256,t_string_storage)": {
            "label": "mapping(uint256 => string)",
            "numberOfBytes": "32"
          },
          "t_string_storage": {
            "label": "string",
            "numberOfBytes": "32"
          },
          "t_struct(Counter)2494_storage": {
            "label": "struct CountersUpgradeable.Counter",
            "members": [
              {
                "label": "_value",
                "type": "t_uint256",
                "offset": 0,
                "slot": "0"
              }
            ],
            "numberOfBytes": "32"
          },
          "t_uint256": {
            "label": "uint256",
            "numberOfBytes": "32"
          },
          "t_uint8": {
            "label": "uint8",
            "numberOfBytes": "1"
          }
        }
      }
    },
    "115481821ae7950c8b05c71b5154cc155da1866e33c1bc58e6bea54b5b232118": {
      "address": "0x094b5f75AfE89aCbbE9c22fFb4AE64ab0BdeEA02",
      "txHash": "0xa5ee793a8b086a773e0943edbc42ccbe9650b8b6df774e5a5a0018f886b3edb4",
      "layout": {
        "solcVersion": "0.8.17",
        "storage": [
          {
            "label": "_initialized",
            "offset": 0,
            "slot": "0",
            "type": "t_uint8",
            "contract": "Initializable",
            "src": "@openzeppelin/contracts-upgradeable/proxy/utils/Initializable.sol:62",
            "retypedFrom": "bool"
          },
          {
            "label": "_initializing",
            "offset": 1,
            "slot": "0",
            "type": "t_bool",
            "contract": "Initializable",
            "src": "@openzeppelin/contracts-upgradeable/proxy/utils/Initializable.sol:67"
          },
          {
            "label": "__gap",
            "offset": 0,
            "slot": "1",
            "type": "t_array(t_uint256)50_storage",
            "contract": "ContextUpgradeable",
            "src": "@openzeppelin/contracts-upgradeable/utils/ContextUpgradeable.sol:36"
          },
          {
            "label": "__gap",
            "offset": 0,
            "slot": "51",
            "type": "t_array(t_uint256)50_storage",
            "contract": "ERC165Upgradeable",
            "src": "@openzeppelin/contracts-upgradeable/utils/introspection/ERC165Upgradeable.sol:41"
          },
          {
            "label": "_name",
            "offset": 0,
            "slot": "101",
            "type": "t_string_storage",
            "contract": "ERC721Upgradeable",
            "src": "@openzeppelin/contracts-upgradeable/token/ERC721/ERC721Upgradeable.sol:25"
          },
          {
            "label": "_symbol",
            "offset": 0,
            "slot": "102",
            "type": "t_string_storage",
            "contract": "ERC721Upgradeable",
            "src": "@openzeppelin/contracts-upgradeable/token/ERC721/ERC721Upgradeable.sol:28"
          },
          {
            "label": "_owners",
            "offset": 0,
            "slot": "103",
            "type": "t_mapping(t_uint256,t_address)",
            "contract": "ERC721Upgradeable",
            "src": "@openzeppelin/contracts-upgradeable/token/ERC721/ERC721Upgradeable.sol:31"
          },
          {
            "label": "_balances",
            "offset": 0,
            "slot": "104",
            "type": "t_mapping(t_address,t_uint256)",
            "contract": "ERC721Upgradeable",
            "src": "@openzeppelin/contracts-upgradeable/token/ERC721/ERC721Upgradeable.sol:34"
          },
          {
            "label": "_tokenApprovals",
            "offset": 0,
            "slot": "105",
            "type": "t_mapping(t_uint256,t_address)",
            "contract": "ERC721Upgradeable",
            "src": "@openzeppelin/contracts-upgradeable/token/ERC721/ERC721Upgradeable.sol:37"
          },
          {
            "label": "_operatorApprovals",
            "offset": 0,
            "slot": "106",
            "type": "t_mapping(t_address,t_mapping(t_address,t_bool))",
            "contract": "ERC721Upgradeable",
            "src": "@openzeppelin/contracts-upgradeable/token/ERC721/ERC721Upgradeable.sol:40"
          },
          {
            "label": "__gap",
            "offset": 0,
            "slot": "107",
            "type": "t_array(t_uint256)44_storage",
            "contract": "ERC721Upgradeable",
            "src": "@openzeppelin/contracts-upgradeable/token/ERC721/ERC721Upgradeable.sol:532"
          },
          {
            "label": "_tokenURIs",
            "offset": 0,
            "slot": "151",
            "type": "t_mapping(t_uint256,t_string_storage)",
            "contract": "ERC721URIStorageUpgradeable",
            "src": "@openzeppelin/contracts-upgradeable/token/ERC721/extensions/ERC721URIStorageUpgradeable.sol:21"
          },
          {
            "label": "__gap",
            "offset": 0,
            "slot": "152",
            "type": "t_array(t_uint256)49_storage",
            "contract": "ERC721URIStorageUpgradeable",
            "src": "@openzeppelin/contracts-upgradeable/token/ERC721/extensions/ERC721URIStorageUpgradeable.sol:74"
          },
          {
            "label": "__gap",
            "offset": 0,
            "slot": "201",
            "type": "t_array(t_uint256)50_storage",
            "contract": "ERC721BurnableUpgradeable",
            "src": "@openzeppelin/contracts-upgradeable/token/ERC721/extensions/ERC721BurnableUpgradeable.sol:38"
          },
          {
            "label": "_owner",
            "offset": 0,
            "slot": "251",
            "type": "t_address",
            "contract": "OwnableUpgradeable",
            "src": "@openzeppelin/contracts-upgradeable/access/OwnableUpgradeable.sol:22"
          },
          {
            "label": "__gap",
            "offset": 0,
            "slot": "252",
            "type": "t_array(t_uint256)49_storage",
            "contract": "OwnableUpgradeable",
            "src": "@openzeppelin/contracts-upgradeable/access/OwnableUpgradeable.sol:94"
          },
          {
            "label": "__gap",
            "offset": 0,
            "slot": "301",
            "type": "t_array(t_uint256)50_storage",
            "contract": "ERC1967UpgradeUpgradeable",
            "src": "@openzeppelin/contracts-upgradeable/proxy/ERC1967/ERC1967UpgradeUpgradeable.sol:211"
          },
          {
            "label": "__gap",
            "offset": 0,
            "slot": "351",
            "type": "t_array(t_uint256)50_storage",
            "contract": "UUPSUpgradeable",
            "src": "@openzeppelin/contracts-upgradeable/proxy/utils/UUPSUpgradeable.sol:107"
          },
          {
            "label": "_tokenIdCounter",
            "offset": 0,
            "slot": "401",
            "type": "t_struct(Counter)2494_storage",
            "contract": "MyNFT",
            "src": "contracts/MyNFT.sol:15"
          },
          {
            "label": "currentIdCount",
            "offset": 0,
            "slot": "402",
            "type": "t_uint256",
            "contract": "MyNFT",
            "src": "contracts/MyNFT.sol:32"
          }
        ],
        "types": {
          "t_address": {
            "label": "address",
            "numberOfBytes": "20"
          },
          "t_array(t_uint256)44_storage": {
            "label": "uint256[44]",
            "numberOfBytes": "1408"
          },
          "t_array(t_uint256)49_storage": {
            "label": "uint256[49]",
            "numberOfBytes": "1568"
          },
          "t_array(t_uint256)50_storage": {
            "label": "uint256[50]",
            "numberOfBytes": "1600"
          },
          "t_bool": {
            "label": "bool",
            "numberOfBytes": "1"
          },
          "t_mapping(t_address,t_bool)": {
            "label": "mapping(address => bool)",
            "numberOfBytes": "32"
          },
          "t_mapping(t_address,t_mapping(t_address,t_bool))": {
            "label": "mapping(address => mapping(address => bool))",
            "numberOfBytes": "32"
          },
          "t_mapping(t_address,t_uint256)": {
            "label": "mapping(address => uint256)",
            "numberOfBytes": "32"
          },
          "t_mapping(t_uint256,t_address)": {
            "label": "mapping(uint256 => address)",
            "numberOfBytes": "32"
          },
          "t_mapping(t_uint256,t_string_storage)": {
            "label": "mapping(uint256 => string)",
            "numberOfBytes": "32"
          },
          "t_string_storage": {
            "label": "string",
            "numberOfBytes": "32"
          },
          "t_struct(Counter)2494_storage": {
            "label": "struct CountersUpgradeable.Counter",
            "members": [
              {
                "label": "_value",
                "type": "t_uint256",
                "offset": 0,
                "slot": "0"
              }
            ],
            "numberOfBytes": "32"
          },
          "t_uint256": {
            "label": "uint256",
            "numberOfBytes": "32"
          },
          "t_uint8": {
            "label": "uint8",
            "numberOfBytes": "1"
          }
        }
      }
    },
    "dafde14d0cbdcba0a1e395e9bcf421dd1b8ef87780d1945f3634a3ca7390eb6c": {
      "address": "0x7190da53b7D7400085b31FA3e26721bf53671808",
      "txHash": "0xc3463d139dc3a8c3b7084f86b50391b3484ce6586e1c29e7b59edfbfaf354545",
      "layout": {
        "solcVersion": "0.8.17",
        "storage": [
          {
            "label": "_initialized",
            "offset": 0,
            "slot": "0",
            "type": "t_uint8",
            "contract": "Initializable",
            "src": "@openzeppelin/contracts-upgradeable/proxy/utils/Initializable.sol:62",
            "retypedFrom": "bool"
          },
          {
            "label": "_initializing",
            "offset": 1,
            "slot": "0",
            "type": "t_bool",
            "contract": "Initializable",
            "src": "@openzeppelin/contracts-upgradeable/proxy/utils/Initializable.sol:67"
          },
          {
            "label": "__gap",
            "offset": 0,
            "slot": "1",
            "type": "t_array(t_uint256)50_storage",
            "contract": "ContextUpgradeable",
            "src": "@openzeppelin/contracts-upgradeable/utils/ContextUpgradeable.sol:36"
          },
          {
            "label": "__gap",
            "offset": 0,
            "slot": "51",
            "type": "t_array(t_uint256)50_storage",
            "contract": "ERC165Upgradeable",
            "src": "@openzeppelin/contracts-upgradeable/utils/introspection/ERC165Upgradeable.sol:41"
          },
          {
            "label": "_name",
            "offset": 0,
            "slot": "101",
            "type": "t_string_storage",
            "contract": "ERC721Upgradeable",
            "src": "@openzeppelin/contracts-upgradeable/token/ERC721/ERC721Upgradeable.sol:25"
          },
          {
            "label": "_symbol",
            "offset": 0,
            "slot": "102",
            "type": "t_string_storage",
            "contract": "ERC721Upgradeable",
            "src": "@openzeppelin/contracts-upgradeable/token/ERC721/ERC721Upgradeable.sol:28"
          },
          {
            "label": "_owners",
            "offset": 0,
            "slot": "103",
            "type": "t_mapping(t_uint256,t_address)",
            "contract": "ERC721Upgradeable",
            "src": "@openzeppelin/contracts-upgradeable/token/ERC721/ERC721Upgradeable.sol:31"
          },
          {
            "label": "_balances",
            "offset": 0,
            "slot": "104",
            "type": "t_mapping(t_address,t_uint256)",
            "contract": "ERC721Upgradeable",
            "src": "@openzeppelin/contracts-upgradeable/token/ERC721/ERC721Upgradeable.sol:34"
          },
          {
            "label": "_tokenApprovals",
            "offset": 0,
            "slot": "105",
            "type": "t_mapping(t_uint256,t_address)",
            "contract": "ERC721Upgradeable",
            "src": "@openzeppelin/contracts-upgradeable/token/ERC721/ERC721Upgradeable.sol:37"
          },
          {
            "label": "_operatorApprovals",
            "offset": 0,
            "slot": "106",
            "type": "t_mapping(t_address,t_mapping(t_address,t_bool))",
            "contract": "ERC721Upgradeable",
            "src": "@openzeppelin/contracts-upgradeable/token/ERC721/ERC721Upgradeable.sol:40"
          },
          {
            "label": "__gap",
            "offset": 0,
            "slot": "107",
            "type": "t_array(t_uint256)44_storage",
            "contract": "ERC721Upgradeable",
            "src": "@openzeppelin/contracts-upgradeable/token/ERC721/ERC721Upgradeable.sol:532"
          },
          {
            "label": "_tokenURIs",
            "offset": 0,
            "slot": "151",
            "type": "t_mapping(t_uint256,t_string_storage)",
            "contract": "ERC721URIStorageUpgradeable",
            "src": "@openzeppelin/contracts-upgradeable/token/ERC721/extensions/ERC721URIStorageUpgradeable.sol:21"
          },
          {
            "label": "__gap",
            "offset": 0,
            "slot": "152",
            "type": "t_array(t_uint256)49_storage",
            "contract": "ERC721URIStorageUpgradeable",
            "src": "@openzeppelin/contracts-upgradeable/token/ERC721/extensions/ERC721URIStorageUpgradeable.sol:74"
          },
          {
            "label": "__gap",
            "offset": 0,
            "slot": "201",
            "type": "t_array(t_uint256)50_storage",
            "contract": "ERC721BurnableUpgradeable",
            "src": "@openzeppelin/contracts-upgradeable/token/ERC721/extensions/ERC721BurnableUpgradeable.sol:38"
          },
          {
            "label": "_owner",
            "offset": 0,
            "slot": "251",
            "type": "t_address",
            "contract": "OwnableUpgradeable",
            "src": "@openzeppelin/contracts-upgradeable/access/OwnableUpgradeable.sol:22"
          },
          {
            "label": "__gap",
            "offset": 0,
            "slot": "252",
            "type": "t_array(t_uint256)49_storage",
            "contract": "OwnableUpgradeable",
            "src": "@openzeppelin/contracts-upgradeable/access/OwnableUpgradeable.sol:94"
          },
          {
            "label": "__gap",
            "offset": 0,
            "slot": "301",
            "type": "t_array(t_uint256)50_storage",
            "contract": "ERC1967UpgradeUpgradeable",
            "src": "@openzeppelin/contracts-upgradeable/proxy/ERC1967/ERC1967UpgradeUpgradeable.sol:211"
          },
          {
            "label": "__gap",
            "offset": 0,
            "slot": "351",
            "type": "t_array(t_uint256)50_storage",
            "contract": "UUPSUpgradeable",
            "src": "@openzeppelin/contracts-upgradeable/proxy/utils/UUPSUpgradeable.sol:107"
          },
          {
            "label": "_tokenIdCounter",
            "offset": 0,
            "slot": "401",
            "type": "t_struct(Counter)2494_storage",
            "contract": "MyNFT",
            "src": "contracts/MyNFT.sol:15"
          },
          {
            "label": "currentIdCount",
            "offset": 0,
            "slot": "402",
            "type": "t_uint256",
            "contract": "MyNFT",
            "src": "contracts/MyNFT.sol:33"
          }
        ],
        "types": {
          "t_address": {
            "label": "address",
            "numberOfBytes": "20"
          },
          "t_array(t_uint256)44_storage": {
            "label": "uint256[44]",
            "numberOfBytes": "1408"
          },
          "t_array(t_uint256)49_storage": {
            "label": "uint256[49]",
            "numberOfBytes": "1568"
          },
          "t_array(t_uint256)50_storage": {
            "label": "uint256[50]",
            "numberOfBytes": "1600"
          },
          "t_bool": {
            "label": "bool",
            "numberOfBytes": "1"
          },
          "t_mapping(t_address,t_bool)": {
            "label": "mapping(address => bool)",
            "numberOfBytes": "32"
          },
          "t_mapping(t_address,t_mapping(t_address,t_bool))": {
            "label": "mapping(address => mapping(address => bool))",
            "numberOfBytes": "32"
          },
          "t_mapping(t_address,t_uint256)": {
            "label": "mapping(address => uint256)",
            "numberOfBytes": "32"
          },
          "t_mapping(t_uint256,t_address)": {
            "label": "mapping(uint256 => address)",
            "numberOfBytes": "32"
          },
          "t_mapping(t_uint256,t_string_storage)": {
            "label": "mapping(uint256 => string)",
            "numberOfBytes": "32"
          },
          "t_string_storage": {
            "label": "string",
            "numberOfBytes": "32"
          },
          "t_struct(Counter)2494_storage": {
            "label": "struct CountersUpgradeable.Counter",
            "members": [
              {
                "label": "_value",
                "type": "t_uint256",
                "offset": 0,
                "slot": "0"
              }
            ],
            "numberOfBytes": "32"
          },
          "t_uint256": {
            "label": "uint256",
            "numberOfBytes": "32"
          },
          "t_uint8": {
            "label": "uint8",
            "numberOfBytes": "1"
          }
        }
      }
    }
  }
}
